[{"id":1,"function":"stamina","resetPriceList":"11999/5#11999/10#11999/20#11999/30#11999/50"},{"id":2,"function":"daily_challenge1","resetPriceList":"11999/10#11999/30#11999/50"},{"id":3,"function":"daily_challenge2","resetPriceList":"11999/10#11999/30#11999/50"},{"id":4,"function":"daily_challenge3","resetPriceList":"11999/10#11999/30#11999/50"},{"id":5,"function":"arena","resetPriceList":"11999/5#11999/10#11999/20#11999/30#11999/50"},{"id":6,"function":"chaos_castle","resetPriceList":"11999/50#11999/100#11999/200#11999/300#11999/500"}]